dame/__init__.py
dame/dataset.py
dame/source.py
dame/stages.py
dame/storage.py
dame/versionable.py
dame/worker.py
tests/__init__.py
tests/test_classes.py
tests/test_dataset.py
tests/test_source.py
tests/test_stages.py
tests/test_storage.py
tests/test_versionable.py
tests/test_worker.py
dame-0.0.2.dist-info/LICENSE
dame-0.0.2.dist-info/METADATA
dame-0.0.2.dist-info/WHEEL
dame-0.0.2.dist-info/top_level.txt
dame-0.0.2.dist-info/RECORD
