Metadata-Version: 2.1
Name: dame
Version: 0.0.2
Summary: Manage your dataflows seamlessly
Home-page: https://github.com/malpunek/dame
Author: Stanisław Morawski
Author-email: stas.morawski@gmail.com
License: UNKNOWN
Platform: UNKNOWN
Classifier: Programming Language :: Python :: 3
Classifier: License :: OSI Approved :: MIT License
Classifier: Operating System :: OS Independent
Classifier: Development Status :: 1 - Planning
Classifier: Topic :: Software Development
Requires-Python: >=3.6
Requires-Dist: numpy
Requires-Dist: peewee (>=3)
